google_apis_oauth/__init__.py
google_apis_oauth/exceptions.py
google_apis_oauth_django-1.0.0.dist-info/LICENSE
google_apis_oauth_django-1.0.0.dist-info/METADATA
google_apis_oauth_django-1.0.0.dist-info/WHEEL
google_apis_oauth_django-1.0.0.dist-info/top_level.txt
google_apis_oauth_django-1.0.0.dist-info/RECORD
