Metadata-Version: 2.1
Name: google-apis-oauth-django
Version: 1.0.0
Summary: A library to help integrate Google OAuth 2.0 to your Django application.
Home-page: https://github.com/nishantwrp/google-apis-oauth-django
Author: Nishant Mittal
Author-email: admin@nishantwrp.com
License: MIT License
Platform: UNKNOWN
License-File: LICENSE
